cloudmesh_pi_cluster-4.3.14-py3.9-nspkg.pth
cloudmesh/bridge/Bridge.py
cloudmesh/bridge/__init__.py
cloudmesh/bridge/command/__init__.py
cloudmesh/bridge/command/bridge.py
cloudmesh/pi/__init__.py
cloudmesh/pi/__version__.py
cloudmesh/pi/wifi.py
cloudmesh/pi/board/__init__.py
cloudmesh/pi/board/free.py
cloudmesh/pi/board/led.py
cloudmesh/pi/board/load.py
cloudmesh/pi/board/monitor.py
cloudmesh/pi/board/temperature.py
cloudmesh/pi/cluster/Installer.py
cloudmesh/pi/cluster/__init__.py
cloudmesh/pi/command/__init__.py
cloudmesh/pi/command/pi.py
cloudmesh_pi_cluster-4.3.14.dist-info/LICENSE
cloudmesh_pi_cluster-4.3.14.dist-info/METADATA
cloudmesh_pi_cluster-4.3.14.dist-info/WHEEL
cloudmesh_pi_cluster-4.3.14.dist-info/namespace_packages.txt
cloudmesh_pi_cluster-4.3.14.dist-info/top_level.txt
cloudmesh_pi_cluster-4.3.14.dist-info/RECORD
