Metadata-Version: 2.1
Name: cloudmesh-pi-cluster
Version: 4.3.14
Summary: A command called pi and foo for the cloudmesh shell
Home-page: https://github.com/cloudmesh/cloudmesh-pi-cluster
Author: Gregor von Laszewski
Author-email: laszewski@gmail.com
License: Apache 2.0
Platform: UNKNOWN
Classifier: Development Status :: 5 - Production/Stable
Classifier: Environment :: Web Environment
Classifier: Intended Audience :: Developers
Classifier: License :: OSI Approved :: BSD License
Classifier: Operating System :: OS Independent
Classifier: Programming Language :: Python :: 3
Classifier: Programming Language :: Python :: 3.7
Classifier: Programming Language :: Python :: 3.8
Requires-Dist: cloudmesh-cmd5
Requires-Dist: cloudmesh-sys
Requires-Dist: cloudmesh-inventory
Requires-Dist: cloudmesh-configuration
Requires-Dist: cloudmesh-ssh
Requires-Dist: cloudmesh-pi-burn
Requires-Dist: pygal
Requires-Dist: matplotlib
Requires-Dist: humanize
Requires-Dist: md-toc
